mikiApi/mikiApi.py
mikiApi-1.0.0.dist-info/METADATA
mikiApi-1.0.0.dist-info/WHEEL
mikiApi-1.0.0.dist-info/top_level.txt
mikiApi-1.0.0.dist-info/RECORD
